{
  "features": [
    {
      "name": "ppc-landing",
      "streamId": "landing-page-new",
      "templateType": "JS",
      "entityPageSet": {}
    }
  ],
  "streams": [
    {
      "$id": "landing-page-new",
      "localization": {
        "locales": [
          "en_GB"
        ],
        "primary": false
      },
      "filter": {
        "entityTypes": [
          "ce_ppcLanding"
        ]
      },
      "fields": [
        "c_headerImage",
        "name",
        "c_whystudy",
        "c_title_arden",
        "c_desc_arden",
        "c_footerImage",
        "slug"
      ],
      "source": "knowledgeGraph",
      "destination": "pages"
    }
  ]
}